MANIFEST.in
README.md
requirements.txt
setup.py
ssh_get_sysinfo.py
ssh_get_sysinfo.egg-info/PKG-INFO
ssh_get_sysinfo.egg-info/SOURCES.txt
ssh_get_sysinfo.egg-info/dependency_links.txt
ssh_get_sysinfo.egg-info/entry_points.txt
ssh_get_sysinfo.egg-info/requires.txt
ssh_get_sysinfo.egg-info/top_level.txt