Metadata-Version: 2.1
Name: ssh-get-sysinfo
Version: 0.1.0
Summary: Get system information via ssh channel.
Home-page: UNKNOWN
Author: zencore
Author-email: info@zencore.cn
License: MIT
Keywords: ssh-get-sysinfo
Platform: UNKNOWN
Classifier: Development Status :: 5 - Production/Stable
Classifier: Intended Audience :: Developers
Classifier: Topic :: Software Development :: Libraries :: Python Modules
Classifier: License :: OSI Approved :: MIT License
Classifier: Programming Language :: Python :: 3
Classifier: Programming Language :: Python :: 3 :: Only
Requires: click
Requires: paramiko
